tmuxer.py
htoolbox-0.3.0.data/scripts/codeit
htoolbox-0.3.0.data/scripts/smagic
htoolbox-0.3.0.dist-info/licenses/LICENSE
htoolbox-0.3.0.dist-info/METADATA
htoolbox-0.3.0.dist-info/WHEEL
htoolbox-0.3.0.dist-info/entry_points.txt
htoolbox-0.3.0.dist-info/top_level.txt
htoolbox-0.3.0.dist-info/RECORD
