Metadata-Version: 2.4
Name: htoolbox
Version: 0.3.0
Summary: This package includes various tools for developers.
Requires-Python: >=3.12
License-File: LICENSE
Requires-Dist: pip>=25.3
Dynamic: license-file
